VUW/__init__.py
VUW/add_mon.py
VUW/add_year.py
VUW/cut_age.py
VUW/get_kcd.py
VUW/glue_code.py
VUW/id_with_kcd_terms.py
VUW/in_ith_mon.py
VUW/in_ith_year.py
VUW/kcd_in_ith_mon.py
VUW/kcd_in_ith_year.py
VUW/map_kcd.py
VUW/merge_overlapping_date_range.py
VUW/proc_time.py
VUW/rm_cols.py
VUW/split_date_range.py
VUW/subset_id_with_kcd_.py
VUW/subset_id_with_kcd_terms.py
vuw-1.2.0.dist-info/METADATA
vuw-1.2.0.dist-info/WHEEL
vuw-1.2.0.dist-info/top_level.txt
vuw-1.2.0.dist-info/RECORD
